{
    "_battery": {},
    "_battery_neg_wire": {
        "start": [
            1250,
            342.4
        ],
        "end": [
            1162,
            354.4
        ],
        "color": [
            0,
            0,
            0
        ],
        "terminal_type": "neg",
        "endpoint_tag": "_battery_neg_wire_endpoint"
    },
    "_battery_pos_wire": {
        "start": [
            1250,
            439.6
        ],
        "end": [
            1162,
            451.6
        ],
        "color": [
            255,
            0,
            0
        ],
        "terminal_type": "pos",
        "endpoint_tag": "_battery_pos_wire_endpoint"
    },
    "_chip_0": {
        "XY": [
            130.5,
            161.5
        ],
        "pinUL_XY": [
            132.5,
            152.5
        ],
        "chipWidth": 2.4,
        "pinCount": 14,
        "label": "74HC00",
        "type": "74HC00",
        "btnMenu": [
            1,
            1,
            0
        ],
        "symbScript": "NandGate",
        "io": [
            [
                [
                    1,
                    2
                ],
                [
                    3
                ]
            ],
            [
                [
                    4,
                    5
                ],
                [
                    6
                ]
            ],
            [
                [
                    9,
                    10
                ],
                [
                    8
                ]
            ],
            [
                [
                    12,
                    13
                ],
                [
                    11
                ]
            ]
        ],
        "pwr": [
            [
                14,
                "+"
            ],
            [
                7,
                "-"
            ]
        ],
        "logicFunctionName": "NandGate",
        "occupied_holes": [
            "5,7",
            "5,8",
            "6,7",
            "6,8",
            "7,7",
            "7,8",
            "8,7",
            "8,8",
            "9,7",
            "9,8",
            "10,7",
            "10,8",
            "11,7",
            "11,8"
        ]
    },
    "_wire_0": {
        "mode": 0,
        "coord": [
            [
                5,
                2,
                5,
                3
            ]
        ],
        "multipoints": [],
        "color": [
            255,
            38,
            0
        ],
        "wire_body_tag": "_wire_0_body",
        "endpoints": {
            "start": {
                "position": [
                    132.5,
                    47.5
                ],
                "tag": "_wire_0_start"
            },
            "end": {
                "position": [
                    132.5,
                    92.5
                ],
                "tag": "_wire_0_end"
            }
        }
    },
    "_wire_1": {
        "mode": 0,
        "coord": [
            [
                11,
                9,
                12,
                1
            ]
        ],
        "multipoints": [
            186,
            203
        ],
        "color": [
            0,
            0,
            0
        ],
        "wire_body_tag": "_wire_1_body",
        "endpoints": {
            "start": {
                "position": [
                    222.5,
                    212.5
                ],
                "tag": "_wire_1_start"
            },
            "end": {
                "position": [
                    237.5,
                    32.5
                ],
                "tag": "_wire_1_end"
            }
        }
    },
    "_wire_4": {
        "mode": 0,
        "coord": [
            [
                61,
                1,
                61,
                13
            ]
        ],
        "multipoints": [],
        "color": [
            0,
            0,
            0
        ],
        "wire_body_tag": "_wire_4_body",
        "endpoints": {
            "start": {
                "position": [
                    972.5,
                    32.5
                ],
                "tag": "_wire_4_start"
            },
            "end": {
                "position": [
                    972.5,
                    302.5
                ],
                "tag": "_wire_4_end"
            }
        }
    },
    "_io_3": {
        "coord": [
            [
                7,
                11
            ]
        ],
        "XY": [
            112.5,
            232.5
        ],
        "controller_pin": "IO",
        "type": 1,
        "color": "#479dff",
        "outline_tag": "pin_io_outline__io_3",
        "tag": "pin_io__io_3",
        "label_tag": "_io_3_label"
    },
    "_io_4": {
        "coord": [
            [
                5,
                12
            ]
        ],
        "XY": [
            82.5,
            247.5
        ],
        "controller_pin": "IO",
        "type": 0,
        "color": "#479dff",
        "outline_tag": "pin_io_outline__io_4",
        "tag": "pin_io__io_4",
        "label_tag": "_io_4_label"
    },
    "_wire_5": {
        "mode": 0,
        "coord": [
            [
                6,
                12,
                7,
                12
            ]
        ],
        "multipoints": [],
        "color": [
            71,
            157,
            255
        ],
        "wire_body_tag": "_wire_5_body",
        "endpoints": {
            "start": {
                "position": [
                    147.5,
                    257.5
                ],
                "tag": "_wire_5_start"
            },
            "end": {
                "position": [
                    147.5,
                    257.5
                ],
                "tag": "_wire_5_end"
            }
        }
    }
}